easy_signer/__init__.py
easy_signer/baseconv.py
easy_signer/crypto.py
easy_signer/defaults.py
easy_signer/encoding.py
easy_signer/exceptions.py
easy_signer/serializers.py
easy_signer/signers.py
easy_signer-0.1.0.dist-info/LICENSE
easy_signer-0.1.0.dist-info/METADATA
easy_signer-0.1.0.dist-info/WHEEL
easy_signer-0.1.0.dist-info/top_level.txt
easy_signer-0.1.0.dist-info/zip-safe
easy_signer-0.1.0.dist-info/RECORD
