Metadata-Version: 2.1
Name: easy-signer
Version: 0.1.0
Summary: Simple package for cryptographic signing
Home-page: https://github.com/paaksing/easy_signer
Author: Paaksing
Author-email: paaksingtech@gmail.com
License: MIT
Keywords: signing,cryptographic,security
Classifier: Development Status :: 5 - Production/Stable
Classifier: Programming Language :: Python :: 3.8
Classifier: Environment :: Web Environment
Classifier: Operating System :: OS Independent
Classifier: Intended Audience :: Developers
Classifier: License :: OSI Approved :: MIT License
Classifier: Topic :: Software Development :: Libraries :: Python Modules
Classifier: Natural Language :: English
License-File: LICENSE
Requires-Dist: orjson (>=3)
